bws/__init__.py
bws/package.json
bws/plopfile.js
bws/admin/__init__.py
bws/admin/bootstrap.py
bws/admin/json.py
bws/admin/urls.py
bws/admin/view.py
bws/cmd/__init__.py
bws/cmd/base.py
bws/cmd/create_app.py
bws/cmd/create_project.py
bws/plop-templates/Component.js.hbs
bws/templates/__init__.py
bws/templates/cmd.py
bws/templates/config.py
bws/templates/env.py
bws/templates/migrate.py
bws/templates/pipfile.py
bws/templates/readme.py
bws/templates/setting.py
bws/templates/web.py
bws/templates/app/api.py
bws/templates/app/cmd.py
bws/templates/app/config.py
bws/templates/app/migrations.py
bws/templates/app/models.py
bws/templates/app/view.py
bws/utils/__init__.py
bws/utils/datetime.py
bws/utils/format.py
bws-0.0.2.dist-info/entry_points.txt
bws-0.0.2.dist-info/LICENSE
bws-0.0.2.dist-info/WHEEL
bws-0.0.2.dist-info/METADATA
bws-0.0.2.dist-info/RECORD
